sheet_logger/__init__.py
sheet_logger/sheet_logger.py
tests/__init__.py
tests/test_sheet_logger.py
sheet_logger-1.1.0.2.dist-info/LICENSE
sheet_logger-1.1.0.2.dist-info/METADATA
sheet_logger-1.1.0.2.dist-info/WHEEL
sheet_logger-1.1.0.2.dist-info/top_level.txt
sheet_logger-1.1.0.2.dist-info/RECORD
