Metadata-Version: 2.1
Name: sheet-logger
Version: 1.1.0.2
Summary: A Google Sheets log printer with batching and API rate limit checks
Home-page: https://github.com/Locaria/SheetLogger
Author: Thorsten Brueckner
Author-email: thorsten.brueckner@locaria.com
Classifier: Programming Language :: Python :: 3
Classifier: License :: OSI Approved :: MIT License
Classifier: Operating System :: OS Independent
Requires-Python: >=3.6
License-File: LICENSE
Requires-Dist: google-auth
Requires-Dist: google-auth-oauthlib
Requires-Dist: google-auth-httplib2
Requires-Dist: google-api-python-client
Requires-Dist: pytz
